yandex_bot/__init__.py
yandex_bot/bot.py
yandex_bot/types/__init__.py
yandex_bot/types/message.py
yandex_bot-0.0.3.dist-info/LICENCE
yandex_bot-0.0.3.dist-info/METADATA
yandex_bot-0.0.3.dist-info/WHEEL
yandex_bot-0.0.3.dist-info/top_level.txt
yandex_bot-0.0.3.dist-info/RECORD
