Metadata-Version: 2.1
Name: yandex_bot
Version: 0.0.3
Summary: Async bot package fot yandex messenger
Author-email: Ivan Utkin <ivanutkin2001@gmail.com>
Classifier: Programming Language :: Python :: 3
Classifier: License :: OSI Approved :: MIT License
Classifier: Operating System :: OS Independent
Requires-Python: >=3.11
License-File: LICENCE
